{"_version": "v2", "_storm_id": "AL022015", "_source": "ibtracs", "_grid_res_km": 15.0, "_skip_points": 1, "_compute_ms": 10080.9, "_cached_at": "2026-03-31T08:03:16.942257", "_obs_count": 21, "results": [{"storm_id": "2015167N27266", "timestamp": "2015-06-16T00:00:00", "ike_total_tj": 14.19, "ike_hurricane_tj": 0, "ike_tropical_storm_tj": 14.19, "ike_pretty": "14.2 TJ", "lat": 27.0, "lon": -94.3, "wind_field_source": "noaa_quadrant", "max_wind_ms": 23.1, "min_pressure_hpa": 1005.0, "rmw_nm": 50.0, "r34_nm": 135.0, "r64_nm": null, "r34_quadrants": {"NE": 140.0, "SE": 130.0}, "forward_speed_knots": 19.4, "forward_direction_deg": 310.0}, {"storm_id": "2015167N27266", "timestamp": "2015-06-16T06:00:00", "ike_total_tj": 13.3, "ike_hurricane_tj": 0, "ike_tropical_storm_tj": 13.3, "ike_pretty": "13.3 TJ", "lat": 27.6, "lon": -95.2, "wind_field_source": "noaa_quadrant", "max_wind_ms": 23.1, "min_pressure_hpa": 1001.0, "rmw_nm": 50.0, "r34_nm": 130.0, "r64_nm": null, "r34_quadrants": {"NE": 130.0, "SE": 130.0}, "forward_speed_knots": 17.5, "forward_direction_deg": 305.0}, {"storm_id": "2015167N27266", "timestamp": "2015-06-16T12:00:00", "ike_total_tj": 15.84, "ike_hurricane_tj": 0, "ike_tropical_storm_tj": 15.84, "ike_pretty": "15.8 TJ", "lat": 28.0, "lon": -96.0, "wind_field_source": "noaa_quadrant", "max_wind_ms": 25.7, "min_pressure_hpa": 997.0, "rmw_nm": 20.0, "r34_nm": 96.7, "r64_nm": null, "r34_quadrants": {"NE": 130.0, "SE": 130.0, "NW": 30.0}, "forward_speed_knots": 17.5, "forward_direction_deg": 290.0}, {"storm_id": "2015167N27266", "timestamp": "2015-06-16T16:45:00", "ike_total_tj": 15.84, "ike_hurricane_tj": 0, "ike_tropical_storm_tj": 15.84, "ike_pretty": "15.8 TJ", "lat": 28.2, "lon": -96.7, "wind_field_source": "noaa_quadrant", "max_wind_ms": 25.7, "min_pressure_hpa": 997.0, "rmw_nm": 20.0, "r34_nm": 96.7, "r64_nm": null, "r34_quadrants": {"NE": 130.0, "SE": 130.0, "NW": 30.0}, "forward_speed_knots": 5.8, "forward_direction_deg": 285.0}, {"storm_id": "2015167N27266", "timestamp": "2015-06-16T21:00:00", "ike_total_tj": 8.46, "ike_hurricane_tj": 0, "ike_tropical_storm_tj": 8.46, "ike_pretty": "8.5 TJ", "lat": 28.5, "lon": -96.8, "wind_field_source": "noaa_quadrant", "max_wind_ms": 23.1, "min_pressure_hpa": 998.0, "rmw_nm": 20.0, "r34_nm": 70.0, "r64_nm": null, "r34_quadrants": {"NE": 65.0, "SE": 130.0, "NW": 15.0}, "forward_speed_knots": 17.5, "forward_direction_deg": 350.0}, {"storm_id": "2015167N27266", "timestamp": "2015-06-17T03:00:00", "ike_total_tj": 1.72, "ike_hurricane_tj": 0, "ike_tropical_storm_tj": 1.72, "ike_pretty": "1.7 TJ", "lat": 29.7, "lon": -97.0, "wind_field_source": "noaa_quadrant", "max_wind_ms": 18.0, "min_pressure_hpa": 999.0, "rmw_nm": 23.0, "r34_nm": 65.0, "r64_nm": null, "r34_quadrants": {"SE": 65.0}, "forward_speed_knots": 23.3, "forward_direction_deg": 350.0}, {"storm_id": "2015167N27266", "timestamp": "2015-06-17T09:00:00", "ike_total_tj": 5.76, "ike_hurricane_tj": 0, "ike_tropical_storm_tj": 5.76, "ike_pretty": "5.8 TJ", "lat": 31.0, "lon": -97.3, "wind_field_source": "sub_ts_estimate", "max_wind_ms": 15.4, "min_pressure_hpa": 999.0, "rmw_nm": 25.0, "r34_nm": 62.5, "r64_nm": null, "r34_quadrants": null, "forward_speed_knots": 27.2, "forward_direction_deg": 350.0}, {"storm_id": "2015167N27266", "timestamp": "2015-06-17T15:00:00", "ike_total_tj": 6.3, "ike_hurricane_tj": 0, "ike_tropical_storm_tj": 6.3, "ike_pretty": "6.3 TJ", "lat": 32.2, "lon": -97.5, "wind_field_source": "sub_ts_estimate", "max_wind_ms": 14.4, "min_pressure_hpa": 999.0, "rmw_nm": 28.0, "r34_nm": 70.0, "r64_nm": null, "r34_quadrants": null, "forward_speed_knots": 17.5, "forward_direction_deg": 355.0}, {"storm_id": "2015167N27266", "timestamp": "2015-06-17T21:00:00", "ike_total_tj": 5.76, "ike_hurricane_tj": 0, "ike_tropical_storm_tj": 5.76, "ike_pretty": "5.8 TJ", "lat": 33.1, "lon": -97.4, "wind_field_source": "sub_ts_estimate", "max_wind_ms": 12.9, "min_pressure_hpa": 1000.0, "rmw_nm": 30.0, "r34_nm": 75.0, "r64_nm": null, "r34_quadrants": null, "forward_speed_knots": 17.5, "forward_direction_deg": 10.0}, {"storm_id": "2015167N27266", "timestamp": "2015-06-18T03:00:00", "ike_total_tj": 5.76, "ike_hurricane_tj": 0, "ike_tropical_storm_tj": 5.76, "ike_pretty": "5.8 TJ", "lat": 33.9, "lon": -97.1, "wind_field_source": "sub_ts_estimate", "max_wind_ms": 12.9, "min_pressure_hpa": 1001.0, "rmw_nm": 30.0, "r34_nm": 75.0, "r64_nm": null, "r34_quadrants": null, "forward_speed_knots": 15.6, "forward_direction_deg": 25.0}, {"storm_id": "2015167N27266", "timestamp": "2015-06-18T09:00:00", "ike_total_tj": 6.64, "ike_hurricane_tj": 0, "ike_tropical_storm_tj": 6.64, "ike_pretty": "6.6 TJ", "lat": 34.5, "lon": -96.6, "wind_field_source": "sub_ts_estimate", "max_wind_ms": 11.8, "min_pressure_hpa": 1003.0, "rmw_nm": 35.0, "r34_nm": 87.5, "r64_nm": null, "r34_quadrants": null, "forward_speed_knots": 15.6, "forward_direction_deg": 40.0}, {"storm_id": "2015167N27266", "timestamp": "2015-06-18T15:00:00", "ike_total_tj": 6.72, "ike_hurricane_tj": 0, "ike_tropical_storm_tj": 6.72, "ike_pretty": "6.7 TJ", "lat": 35.0, "lon": -95.9, "wind_field_source": "sub_ts_estimate", "max_wind_ms": 9.3, "min_pressure_hpa": 1004.0, "rmw_nm": 45.0, "r34_nm": 112.5, "r64_nm": null, "r34_quadrants": null, "forward_speed_knots": 15.6, "forward_direction_deg": 60.0}, {"storm_id": "2015167N27266", "timestamp": "2015-06-18T21:00:00", "ike_total_tj": 5.76, "ike_hurricane_tj": 0, "ike_tropical_storm_tj": 5.76, "ike_pretty": "5.8 TJ", "lat": 35.4, "lon": -95.0, "wind_field_source": "sub_ts_estimate", "max_wind_ms": 7.7, "min_pressure_hpa": 1005.0, "rmw_nm": 50.0, "r34_nm": 125.0, "r64_nm": null, "r34_quadrants": null, "forward_speed_knots": 17.5, "forward_direction_deg": 65.0}, {"storm_id": "2015167N27266", "timestamp": "2015-06-19T03:00:00", "ike_total_tj": 5.76, "ike_hurricane_tj": 0, "ike_tropical_storm_tj": 5.76, "ike_pretty": "5.8 TJ", "lat": 35.7, "lon": -94.0, "wind_field_source": "sub_ts_estimate", "max_wind_ms": 7.7, "min_pressure_hpa": 1006.0, "rmw_nm": 50.0, "r34_nm": 125.0, "r64_nm": null, "r34_quadrants": null, "forward_speed_knots": 17.5, "forward_direction_deg": 70.0}, {"storm_id": "2015167N27266", "timestamp": "2015-06-19T09:00:00", "ike_total_tj": 5.76, "ike_hurricane_tj": 0, "ike_tropical_storm_tj": 5.76, "ike_pretty": "5.8 TJ", "lat": 36.1, "lon": -92.9, "wind_field_source": "sub_ts_estimate", "max_wind_ms": 7.7, "min_pressure_hpa": 1006.0, "rmw_nm": 50.0, "r34_nm": 125.0, "r64_nm": null, "r34_quadrants": null, "forward_speed_knots": 19.4, "forward_direction_deg": 70.0}, {"storm_id": "2015167N27266", "timestamp": "2015-06-19T15:00:00", "ike_total_tj": 8.3, "ike_hurricane_tj": 0, "ike_tropical_storm_tj": 8.3, "ike_pretty": "8.3 TJ", "lat": 36.6, "lon": -91.6, "wind_field_source": "sub_ts_estimate", "max_wind_ms": 9.3, "min_pressure_hpa": 1006.0, "rmw_nm": 50.0, "r34_nm": 125.0, "r64_nm": null, "r34_quadrants": null, "forward_speed_knots": 25.3, "forward_direction_deg": 60.0}, {"storm_id": "2015167N27266", "timestamp": "2015-06-19T21:00:00", "ike_total_tj": 10.25, "ike_hurricane_tj": 0, "ike_tropical_storm_tj": 10.25, "ike_pretty": "10.2 TJ", "lat": 37.2, "lon": -90.2, "wind_field_source": "sub_ts_estimate", "max_wind_ms": 10.3, "min_pressure_hpa": 1005.0, "rmw_nm": 50.0, "r34_nm": 125.0, "r64_nm": null, "r34_quadrants": null, "forward_speed_knots": 25.3, "forward_direction_deg": 65.0}, {"storm_id": "2015167N27266", "timestamp": "2015-06-20T03:00:00", "ike_total_tj": 8.3, "ike_hurricane_tj": 0, "ike_tropical_storm_tj": 8.3, "ike_pretty": "8.3 TJ", "lat": 37.6, "lon": -88.6, "wind_field_source": "sub_ts_estimate", "max_wind_ms": 9.3, "min_pressure_hpa": 1003.0, "rmw_nm": 50.0, "r34_nm": 125.0, "r64_nm": null, "r34_quadrants": null, "forward_speed_knots": 25.3, "forward_direction_deg": 70.0}, {"storm_id": "2015167N27266", "timestamp": "2015-06-20T09:00:00", "ike_total_tj": 5.76, "ike_hurricane_tj": 0, "ike_tropical_storm_tj": 5.76, "ike_pretty": "5.8 TJ", "lat": 38.0, "lon": -86.8, "wind_field_source": "sub_ts_estimate", "max_wind_ms": 7.7, "min_pressure_hpa": 1002.0, "rmw_nm": 50.0, "r34_nm": 125.0, "r64_nm": null, "r34_quadrants": null, "forward_speed_knots": 31.1, "forward_direction_deg": 75.0}, {"storm_id": "2015167N27266", "timestamp": "2015-06-20T15:00:00", "ike_total_tj": 5.76, "ike_hurricane_tj": 0, "ike_tropical_storm_tj": 5.76, "ike_pretty": "5.8 TJ", "lat": 38.3, "lon": -84.8, "wind_field_source": "sub_ts_estimate", "max_wind_ms": 7.7, "min_pressure_hpa": 1002.0, "rmw_nm": 50.0, "r34_nm": 125.0, "r64_nm": null, "r34_quadrants": null, "forward_speed_knots": 33.0, "forward_direction_deg": 80.0}, {"storm_id": "2015167N27266", "timestamp": "2015-06-20T21:00:00", "ike_total_tj": 5.76, "ike_hurricane_tj": 0, "ike_tropical_storm_tj": 5.76, "ike_pretty": "5.8 TJ", "lat": 38.7, "lon": -82.5, "wind_field_source": "sub_ts_estimate", "max_wind_ms": 7.7, "min_pressure_hpa": 1005.0, "rmw_nm": 50.0, "r34_nm": 125.0, "r64_nm": null, "r34_quadrants": null, "forward_speed_knots": 36.9, "forward_direction_deg": 80.0}]}