{"_version": "v2", "_storm_id": "AL092025", "_source": "ibtracs", "_grid_res_km": 15.0, "_skip_points": 1, "_compute_ms": 0.9, "_cached_at": "2026-03-31T08:12:19.468831", "_obs_count": 38, "results": [{"storm_id": "2025270N21285", "timestamp": "2025-09-26T18:00:00", "ike_total_tj": 74.71, "ike_hurricane_tj": 0, "ike_tropical_storm_tj": 74.71, "ike_pretty": "74.7 TJ", "lat": 20.9, "lon": -74.9, "wind_field_source": "sub_ts_estimate", "max_wind_ms": 15.4, "min_pressure_hpa": 1008.0, "rmw_nm": 90.0, "r34_nm": 225.0, "r64_nm": null, "r34_quadrants": null, "forward_speed_knots": 13.6, "forward_direction_deg": 305.0}, {"storm_id": "2025270N21285", "timestamp": "2025-09-27T00:00:00", "ike_total_tj": 74.71, "ike_hurricane_tj": 0, "ike_tropical_storm_tj": 74.71, "ike_pretty": "74.7 TJ", "lat": 21.3, "lon": -75.5, "wind_field_source": "sub_ts_estimate", "max_wind_ms": 15.4, "min_pressure_hpa": 1006.0, "rmw_nm": 90.0, "r34_nm": 225.0, "r64_nm": null, "r34_quadrants": null, "forward_speed_knots": 9.7, "forward_direction_deg": 310.0}, {"storm_id": "2025270N21285", "timestamp": "2025-09-27T06:00:00", "ike_total_tj": 74.71, "ike_hurricane_tj": 0, "ike_tropical_storm_tj": 74.71, "ike_pretty": "74.7 TJ", "lat": 21.6, "lon": -75.8, "wind_field_source": "sub_ts_estimate", "max_wind_ms": 15.4, "min_pressure_hpa": 1006.0, "rmw_nm": 90.0, "r34_nm": 225.0, "r64_nm": null, "r34_quadrants": null, "forward_speed_knots": 7.8, "forward_direction_deg": 320.0}, {"storm_id": "2025270N21285", "timestamp": "2025-09-27T12:00:00", "ike_total_tj": 59.03, "ike_hurricane_tj": 0, "ike_tropical_storm_tj": 59.03, "ike_pretty": "59.0 TJ", "lat": 21.9, "lon": -76.1, "wind_field_source": "sub_ts_estimate", "max_wind_ms": 15.4, "min_pressure_hpa": 1005.0, "rmw_nm": 80.0, "r34_nm": 200.0, "r64_nm": null, "r34_quadrants": null, "forward_speed_knots": 7.8, "forward_direction_deg": 310.0}, {"storm_id": "2025270N21285", "timestamp": "2025-09-27T18:00:00", "ike_total_tj": 45.2, "ike_hurricane_tj": 0, "ike_tropical_storm_tj": 45.2, "ike_pretty": "45.2 TJ", "lat": 22.1, "lon": -76.4, "wind_field_source": "sub_ts_estimate", "max_wind_ms": 15.4, "min_pressure_hpa": 1005.0, "rmw_nm": 70.0, "r34_nm": 175.0, "r64_nm": null, "r34_quadrants": null, "forward_speed_knots": 7.8, "forward_direction_deg": 310.0}, {"storm_id": "2025270N21285", "timestamp": "2025-09-28T00:00:00", "ike_total_tj": 23.06, "ike_hurricane_tj": 0, "ike_tropical_storm_tj": 23.06, "ike_pretty": "23.1 TJ", "lat": 22.4, "lon": -76.7, "wind_field_source": "sub_ts_estimate", "max_wind_ms": 15.4, "min_pressure_hpa": 1004.0, "rmw_nm": 50.0, "r34_nm": 125.0, "r64_nm": null, "r34_quadrants": null, "forward_speed_knots": 7.8, "forward_direction_deg": 310.0}, {"storm_id": "2025270N21285", "timestamp": "2025-09-28T06:00:00", "ike_total_tj": 14.76, "ike_hurricane_tj": 0, "ike_tropical_storm_tj": 14.76, "ike_pretty": "14.8 TJ", "lat": 22.7, "lon": -77.1, "wind_field_source": "sub_ts_estimate", "max_wind_ms": 15.4, "min_pressure_hpa": 1003.0, "rmw_nm": 40.0, "r34_nm": 100.0, "r64_nm": null, "r34_quadrants": null, "forward_speed_knots": 9.7, "forward_direction_deg": 310.0}, {"storm_id": "2025270N21285", "timestamp": "2025-09-28T12:00:00", "ike_total_tj": 14.76, "ike_hurricane_tj": 0, "ike_tropical_storm_tj": 14.76, "ike_pretty": "14.8 TJ", "lat": 23.1, "lon": -77.4, "wind_field_source": "sub_ts_estimate", "max_wind_ms": 15.4, "min_pressure_hpa": 1001.0, "rmw_nm": 40.0, "r34_nm": 100.0, "r64_nm": null, "r34_quadrants": null, "forward_speed_knots": 11.7, "forward_direction_deg": 350.0}, {"storm_id": "2025270N21285", "timestamp": "2025-09-28T18:00:00", "ike_total_tj": 9.85, "ike_hurricane_tj": 0, "ike_tropical_storm_tj": 9.85, "ike_pretty": "9.8 TJ", "lat": 23.8, "lon": -77.3, "wind_field_source": "noaa_quadrant", "max_wind_ms": 18.0, "min_pressure_hpa": 998.0, "rmw_nm": 40.0, "r34_nm": 110.0, "r64_nm": null, "r34_quadrants": {"NE": 120.0, "SE": 100.0}, "forward_speed_knots": 15.6, "forward_direction_deg": 15.0}, {"storm_id": "2025270N21285", "timestamp": "2025-09-29T00:00:00", "ike_total_tj": 16.88, "ike_hurricane_tj": 0, "ike_tropical_storm_tj": 16.88, "ike_pretty": "16.9 TJ", "lat": 24.6, "lon": -77.1, "wind_field_source": "noaa_quadrant", "max_wind_ms": 18.0, "min_pressure_hpa": 997.0, "rmw_nm": 40.0, "r34_nm": 150.0, "r64_nm": null, "r34_quadrants": {"NE": 150.0, "SE": 150.0}, "forward_speed_knots": 13.6, "forward_direction_deg": 10.0}, {"storm_id": "2025270N21285", "timestamp": "2025-09-29T06:00:00", "ike_total_tj": 16.88, "ike_hurricane_tj": 0, "ike_tropical_storm_tj": 16.88, "ike_pretty": "16.9 TJ", "lat": 25.3, "lon": -77.1, "wind_field_source": "noaa_quadrant", "max_wind_ms": 20.6, "min_pressure_hpa": 995.0, "rmw_nm": 30.0, "r34_nm": 150.0, "r64_nm": null, "r34_quadrants": {"NE": 150.0, "SE": 150.0}, "forward_speed_knots": 17.5, "forward_direction_deg": null}, {"storm_id": "2025270N21285", "timestamp": "2025-09-29T12:00:00", "ike_total_tj": 19.93, "ike_hurricane_tj": 0, "ike_tropical_storm_tj": 19.93, "ike_pretty": "19.9 TJ", "lat": 26.4, "lon": -77.1, "wind_field_source": "noaa_quadrant", "max_wind_ms": 23.1, "min_pressure_hpa": 989.0, "rmw_nm": 30.0, "r34_nm": 105.0, "r64_nm": null, "r34_quadrants": {"NE": 150.0, "SE": 140.0, "SW": 40.0, "NW": 90.0}, "forward_speed_knots": 21.4, "forward_direction_deg": 355.0}, {"storm_id": "2025270N21285", "timestamp": "2025-09-29T18:00:00", "ike_total_tj": 26.87, "ike_hurricane_tj": 0, "ike_tropical_storm_tj": 26.87, "ike_pretty": "26.9 TJ", "lat": 27.3, "lon": -77.3, "wind_field_source": "noaa_quadrant", "max_wind_ms": 25.7, "min_pressure_hpa": 987.0, "rmw_nm": 30.0, "r34_nm": 122.5, "r64_nm": null, "r34_quadrants": {"NE": 150.0, "SE": 120.0, "SW": 70.0, "NW": 150.0}, "forward_speed_knots": 15.6, "forward_direction_deg": 350.0}, {"storm_id": "2025270N21285", "timestamp": "2025-09-30T00:00:00", "ike_total_tj": 26.96, "ike_hurricane_tj": 0, "ike_tropical_storm_tj": 26.96, "ike_pretty": "27.0 TJ", "lat": 28.0, "lon": -77.3, "wind_field_source": "noaa_quadrant", "max_wind_ms": 28.3, "min_pressure_hpa": 985.0, "rmw_nm": 40.0, "r34_nm": 125.0, "r64_nm": null, "r34_quadrants": {"NE": 140.0, "SE": 100.0, "SW": 100.0, "NW": 160.0}, "forward_speed_knots": 13.6, "forward_direction_deg": 5.0}, {"storm_id": "2025270N21285", "timestamp": "2025-09-30T06:00:00", "ike_total_tj": 26.39, "ike_hurricane_tj": 0, "ike_tropical_storm_tj": 26.39, "ike_pretty": "26.4 TJ", "lat": 28.6, "lon": -77.2, "wind_field_source": "noaa_quadrant", "max_wind_ms": 28.3, "min_pressure_hpa": 983.0, "rmw_nm": 40.0, "r34_nm": 125.0, "r64_nm": null, "r34_quadrants": {"NE": 140.0, "SE": 100.0, "SW": 100.0, "NW": 160.0}, "forward_speed_knots": 9.7, "forward_direction_deg": 20.0}, {"storm_id": "2025270N21285", "timestamp": "2025-09-30T12:00:00", "ike_total_tj": 52.42, "ike_hurricane_tj": 13.08, "ike_tropical_storm_tj": 39.34, "ike_pretty": "52.4 TJ", "lat": 28.9, "lon": -76.9, "wind_field_source": "noaa_quadrant", "max_wind_ms": 33.4, "min_pressure_hpa": 981.0, "rmw_nm": 40.0, "r34_nm": 132.5, "r64_nm": 40.0, "r34_quadrants": {"NE": 130.0, "SE": 140.0, "SW": 100.0, "NW": 160.0}, "forward_speed_knots": 11.7, "forward_direction_deg": 60.0}, {"storm_id": "2025270N21285", "timestamp": "2025-09-30T18:00:00", "ike_total_tj": 50.72, "ike_hurricane_tj": 12.88, "ike_tropical_storm_tj": 37.84, "ike_pretty": "50.7 TJ", "lat": 29.2, "lon": -76.0, "wind_field_source": "noaa_quadrant", "max_wind_ms": 36.0, "min_pressure_hpa": 979.0, "rmw_nm": 35.0, "r34_nm": 127.5, "r64_nm": 40.0, "r34_quadrants": {"NE": 120.0, "SE": 150.0, "SW": 100.0, "NW": 140.0}, "forward_speed_knots": 19.4, "forward_direction_deg": 75.0}, {"storm_id": "2025270N21285", "timestamp": "2025-10-01T00:00:00", "ike_total_tj": 57.57, "ike_hurricane_tj": 10.94, "ike_tropical_storm_tj": 46.63, "ike_pretty": "57.6 TJ", "lat": 29.4, "lon": -74.8, "wind_field_source": "noaa_quadrant", "max_wind_ms": 36.0, "min_pressure_hpa": 977.0, "rmw_nm": 30.0, "r34_nm": 152.5, "r64_nm": 40.0, "r34_quadrants": {"NE": 150.0, "SE": 190.0, "SW": 120.0, "NW": 150.0}, "forward_speed_knots": 25.3, "forward_direction_deg": 75.0}, {"storm_id": "2025270N21285", "timestamp": "2025-10-01T06:00:00", "ike_total_tj": 61.16, "ike_hurricane_tj": 11.54, "ike_tropical_storm_tj": 49.62, "ike_pretty": "61.2 TJ", "lat": 29.9, "lon": -73.1, "wind_field_source": "noaa_quadrant", "max_wind_ms": 38.6, "min_pressure_hpa": 973.0, "rmw_nm": 25.0, "r34_nm": 157.5, "r64_nm": 40.0, "r34_quadrants": {"NE": 150.0, "SE": 200.0, "SW": 120.0, "NW": 160.0}, "forward_speed_knots": 31.1, "forward_direction_deg": 65.0}, {"storm_id": "2025270N21285", "timestamp": "2025-10-01T12:00:00", "ike_total_tj": 60.47, "ike_hurricane_tj": 9.7, "ike_tropical_storm_tj": 50.77, "ike_pretty": "60.5 TJ", "lat": 30.7, "lon": -71.4, "wind_field_source": "noaa_quadrant", "max_wind_ms": 41.2, "min_pressure_hpa": 968.0, "rmw_nm": 25.0, "r34_nm": 160.0, "r64_nm": 35.0, "r34_quadrants": {"NE": 150.0, "SE": 210.0, "SW": 120.0, "NW": 160.0}, "forward_speed_knots": 35.0, "forward_direction_deg": 70.0}, {"storm_id": "2025270N21285", "timestamp": "2025-10-01T18:00:00", "ike_total_tj": 60.1, "ike_hurricane_tj": 13.41, "ike_tropical_storm_tj": 46.69, "ike_pretty": "60.1 TJ", "lat": 31.2, "lon": -69.2, "wind_field_source": "noaa_quadrant", "max_wind_ms": 41.2, "min_pressure_hpa": 966.0, "rmw_nm": 20.0, "r34_nm": 162.5, "r64_nm": 36.7, "r34_quadrants": {"NE": 160.0, "SE": 220.0, "SW": 100.0, "NW": 170.0}, "forward_speed_knots": 42.8, "forward_direction_deg": 75.0}, {"storm_id": "2025270N21285", "timestamp": "2025-10-02T00:00:00", "ike_total_tj": 74.17, "ike_hurricane_tj": 18.74, "ike_tropical_storm_tj": 55.43, "ike_pretty": "74.2 TJ", "lat": 31.8, "lon": -66.4, "wind_field_source": "noaa_quadrant", "max_wind_ms": 41.2, "min_pressure_hpa": 971.0, "rmw_nm": 20.0, "r34_nm": 197.5, "r64_nm": 40.0, "r34_quadrants": {"NE": 180.0, "SE": 220.0, "SW": 150.0, "NW": 240.0}, "forward_speed_knots": 52.5, "forward_direction_deg": 75.0}, {"storm_id": "2025270N21285", "timestamp": "2025-10-02T06:00:00", "ike_total_tj": 75.1, "ike_hurricane_tj": 18.46, "ike_tropical_storm_tj": 56.63, "ike_pretty": "75.1 TJ", "lat": 32.6, "lon": -63.2, "wind_field_source": "noaa_quadrant", "max_wind_ms": 41.2, "min_pressure_hpa": 974.0, "rmw_nm": 10.0, "r34_nm": 247.5, "r64_nm": 40.0, "r34_quadrants": {"NE": 270.0, "SE": 220.0, "SW": 200.0, "NW": 300.0}, "forward_speed_knots": 46.7, "forward_direction_deg": 75.0}, {"storm_id": "2025270N21285", "timestamp": "2025-10-02T12:00:00", "ike_total_tj": 53.29, "ike_hurricane_tj": 10.91, "ike_tropical_storm_tj": 42.38, "ike_pretty": "53.3 TJ", "lat": 33.0, "lon": -60.8, "wind_field_source": "noaa_quadrant", "max_wind_ms": 36.0, "min_pressure_hpa": 977.0, "rmw_nm": 10.0, "r34_nm": 322.5, "r64_nm": 30.0, "r34_quadrants": {"NE": 390.0, "SE": 240.0, "SW": 240.0, "NW": 420.0}, "forward_speed_knots": 44.7, "forward_direction_deg": 80.0}, {"storm_id": "2025270N21285", "timestamp": "2025-10-02T18:00:00", "ike_total_tj": 31.03, "ike_hurricane_tj": 0, "ike_tropical_storm_tj": 31.03, "ike_pretty": "31.0 TJ", "lat": 33.5, "lon": -57.5, "wind_field_source": "noaa_quadrant", "max_wind_ms": 30.9, "min_pressure_hpa": 986.0, "rmw_nm": 40.0, "r34_nm": 337.5, "r64_nm": null, "r34_quadrants": {"NE": 420.0, "SE": 240.0, "SW": 240.0, "NW": 450.0}, "forward_speed_knots": 64.1, "forward_direction_deg": 75.0}, {"storm_id": "2025270N21285", "timestamp": "2025-10-03T00:00:00", "ike_total_tj": 21.8, "ike_hurricane_tj": 0, "ike_tropical_storm_tj": 21.8, "ike_pretty": "21.8 TJ", "lat": 34.5, "lon": -53.4, "wind_field_source": "noaa_quadrant", "max_wind_ms": 28.3, "min_pressure_hpa": 990.0, "rmw_nm": 90.0, "r34_nm": 337.5, "r64_nm": null, "r34_quadrants": {"NE": 450.0, "SE": 240.0, "SW": 240.0, "NW": 420.0}, "forward_speed_knots": 56.4, "forward_direction_deg": 70.0}, {"storm_id": "2025270N21285", "timestamp": "2025-10-03T06:00:00", "ike_total_tj": 23.39, "ike_hurricane_tj": 0, "ike_tropical_storm_tj": 23.39, "ike_pretty": "23.4 TJ", "lat": 35.7, "lon": -51.1, "wind_field_source": "noaa_quadrant", "max_wind_ms": 28.3, "min_pressure_hpa": 990.0, "rmw_nm": 90.0, "r34_nm": 322.5, "r64_nm": null, "r34_quadrants": {"NE": 420.0, "SE": 270.0, "SW": 180.0, "NW": 420.0}, "forward_speed_knots": 42.8, "forward_direction_deg": 50.0}, {"storm_id": "2025270N21285", "timestamp": "2025-10-03T12:00:00", "ike_total_tj": 25.15, "ike_hurricane_tj": 0, "ike_tropical_storm_tj": 25.15, "ike_pretty": "25.1 TJ", "lat": 37.3, "lon": -49.3, "wind_field_source": "noaa_quadrant", "max_wind_ms": 28.3, "min_pressure_hpa": 986.0, "rmw_nm": 70.0, "r34_nm": 277.5, "r64_nm": null, "r34_quadrants": {"NE": 390.0, "SE": 270.0, "SW": 150.0, "NW": 300.0}, "forward_speed_knots": 36.9, "forward_direction_deg": 25.0}, {"storm_id": "2025270N21285", "timestamp": "2025-10-03T18:00:00", "ike_total_tj": 27.67, "ike_hurricane_tj": 0, "ike_tropical_storm_tj": 27.67, "ike_pretty": "27.7 TJ", "lat": 38.9, "lon": -49.1, "wind_field_source": "noaa_quadrant", "max_wind_ms": 30.9, "min_pressure_hpa": 979.0, "rmw_nm": 70.0, "r34_nm": 265.0, "r64_nm": null, "r34_quadrants": {"NE": 330.0, "SE": 240.0, "SW": 220.0, "NW": 270.0}, "forward_speed_knots": 23.3, "forward_direction_deg": null}, {"storm_id": "2025270N21285", "timestamp": "2025-10-04T00:00:00", "ike_total_tj": 97.27, "ike_hurricane_tj": 27.68, "ike_tropical_storm_tj": 69.59, "ike_pretty": "97.3 TJ", "lat": 39.7, "lon": -49.0, "wind_field_source": "noaa_quadrant", "max_wind_ms": 33.4, "min_pressure_hpa": 978.0, "rmw_nm": 70.0, "r34_nm": 247.5, "r64_nm": 75.0, "r34_quadrants": {"NE": 300.0, "SE": 210.0, "SW": 240.0, "NW": 240.0}, "forward_speed_knots": 17.5, "forward_direction_deg": 15.0}, {"storm_id": "2025270N21285", "timestamp": "2025-10-04T06:00:00", "ike_total_tj": 41.11, "ike_hurricane_tj": 0, "ike_tropical_storm_tj": 41.11, "ike_pretty": "41.1 TJ", "lat": 40.8, "lon": -48.5, "wind_field_source": "noaa_quadrant", "max_wind_ms": 30.9, "min_pressure_hpa": 979.0, "rmw_nm": 80.0, "r34_nm": 225.0, "r64_nm": null, "r34_quadrants": {"NE": 270.0, "SE": 210.0, "SW": 240.0, "NW": 180.0}, "forward_speed_knots": 25.3, "forward_direction_deg": 25.0}, {"storm_id": "2025270N21285", "timestamp": "2025-10-04T12:00:00", "ike_total_tj": 36.35, "ike_hurricane_tj": 0, "ike_tropical_storm_tj": 36.35, "ike_pretty": "36.4 TJ", "lat": 42.0, "lon": -47.5, "wind_field_source": "noaa_quadrant", "max_wind_ms": 28.3, "min_pressure_hpa": 981.0, "rmw_nm": 80.0, "r34_nm": 187.5, "r64_nm": null, "r34_quadrants": {"NE": 180.0, "SE": 210.0, "SW": 240.0, "NW": 120.0}, "forward_speed_knots": 33.0, "forward_direction_deg": 35.0}, {"storm_id": "2025270N21285", "timestamp": "2025-10-04T18:00:00", "ike_total_tj": 35.65, "ike_hurricane_tj": 0, "ike_tropical_storm_tj": 35.65, "ike_pretty": "35.6 TJ", "lat": 43.5, "lon": -45.8, "wind_field_source": "noaa_quadrant", "max_wind_ms": 25.7, "min_pressure_hpa": 983.0, "rmw_nm": 70.0, "r34_nm": 180.0, "r64_nm": null, "r34_quadrants": {"NE": 150.0, "SE": 210.0, "SW": 240.0, "NW": 120.0}, "forward_speed_knots": 40.8, "forward_direction_deg": 35.0}, {"storm_id": "2025270N21285", "timestamp": "2025-10-05T00:00:00", "ike_total_tj": 32.69, "ike_hurricane_tj": 0, "ike_tropical_storm_tj": 32.69, "ike_pretty": "32.7 TJ", "lat": 45.3, "lon": -44.0, "wind_field_source": "noaa_quadrant", "max_wind_ms": 23.1, "min_pressure_hpa": 984.0, "rmw_nm": 70.0, "r34_nm": 187.5, "r64_nm": null, "r34_quadrants": {"NE": 120.0, "SE": 240.0, "SW": 270.0, "NW": 120.0}, "forward_speed_knots": 42.8, "forward_direction_deg": 40.0}, {"storm_id": "2025270N21285", "timestamp": "2025-10-05T06:00:00", "ike_total_tj": 37.48, "ike_hurricane_tj": 0, "ike_tropical_storm_tj": 37.48, "ike_pretty": "37.5 TJ", "lat": 46.9, "lon": -41.9, "wind_field_source": "noaa_quadrant", "max_wind_ms": 23.1, "min_pressure_hpa": 984.0, "rmw_nm": 70.0, "r34_nm": 195.0, "r64_nm": null, "r34_quadrants": {"NE": 120.0, "SE": 230.0, "SW": 250.0, "NW": 180.0}, "forward_speed_knots": 42.8, "forward_direction_deg": 40.0}, {"storm_id": "2025270N21285", "timestamp": "2025-10-05T12:00:00", "ike_total_tj": 39.83, "ike_hurricane_tj": 0, "ike_tropical_storm_tj": 39.83, "ike_pretty": "39.8 TJ", "lat": 48.6, "lon": -39.6, "wind_field_source": "noaa_quadrant", "max_wind_ms": 25.7, "min_pressure_hpa": 983.0, "rmw_nm": 80.0, "r34_nm": 207.5, "r64_nm": null, "r34_quadrants": {"NE": 140.0, "SE": 220.0, "SW": 230.0, "NW": 240.0}, "forward_speed_knots": 42.8, "forward_direction_deg": 55.0}, {"storm_id": "2025270N21285", "timestamp": "2025-10-05T18:00:00", "ike_total_tj": 39.83, "ike_hurricane_tj": 0, "ike_tropical_storm_tj": 39.83, "ike_pretty": "39.8 TJ", "lat": 49.5, "lon": -36.5, "wind_field_source": "noaa_quadrant", "max_wind_ms": 25.7, "min_pressure_hpa": 984.0, "rmw_nm": 80.0, "r34_nm": 205.0, "r64_nm": null, "r34_quadrants": {"NE": 140.0, "SE": 210.0, "SW": 230.0, "NW": 240.0}, "forward_speed_knots": 44.7, "forward_direction_deg": 70.0}, {"storm_id": "2025270N21285", "timestamp": "2025-10-06T00:00:00", "ike_total_tj": 35.77, "ike_hurricane_tj": 0, "ike_tropical_storm_tj": 35.77, "ike_pretty": "35.8 TJ", "lat": 50.3, "lon": -33.0, "wind_field_source": "noaa_quadrant", "max_wind_ms": 23.1, "min_pressure_hpa": 988.0, "rmw_nm": 80.0, "r34_nm": 175.0, "r64_nm": null, "r34_quadrants": {"NE": 100.0, "SE": 180.0, "SW": 210.0, "NW": 210.0}, "forward_speed_knots": 46.7, "forward_direction_deg": 70.0}]}